ChangeLog.rst
LICENSE
MANIFEST.in
README.rst
setup.cfg
setup.py
src/fastzbarlight/__init__.py
src/fastzbarlight/_zbarlight.c
src/fastzbarlight/package_data.txt
src/fastzbarlight.egg-info/PKG-INFO
src/fastzbarlight.egg-info/SOURCES.txt
src/fastzbarlight.egg-info/dependency_links.txt
src/fastzbarlight.egg-info/not-zip-safe
src/fastzbarlight.egg-info/requires.txt
src/fastzbarlight.egg-info/top_level.txt
src/fastzbarlight/vendor/Makefile
src/fastzbarlight/vendor/zbar-0.10.tar.bz2.sha
src/fastzbarlight/vendor/zbar-0.10/#configure#
src/fastzbarlight/vendor/zbar-0.10/COPYING
src/fastzbarlight/vendor/zbar-0.10/ChangeLog
src/fastzbarlight/vendor/zbar-0.10/HACKING
src/fastzbarlight/vendor/zbar-0.10/INSTALL
src/fastzbarlight/vendor/zbar-0.10/LICENSE
src/fastzbarlight/vendor/zbar-0.10/Makefile
src/fastzbarlight/vendor/zbar-0.10/Makefile.am
src/fastzbarlight/vendor/zbar-0.10/Makefile.in
src/fastzbarlight/vendor/zbar-0.10/NEWS
src/fastzbarlight/vendor/zbar-0.10/README
src/fastzbarlight/vendor/zbar-0.10/README.windows
src/fastzbarlight/vendor/zbar-0.10/TODO
src/fastzbarlight/vendor/zbar-0.10/aclocal.m4
src/fastzbarlight/vendor/zbar-0.10/config.log
src/fastzbarlight/vendor/zbar-0.10/config.status
src/fastzbarlight/vendor/zbar-0.10/configure
src/fastzbarlight/vendor/zbar-0.10/configure.ac
src/fastzbarlight/vendor/zbar-0.10/libtool
src/fastzbarlight/vendor/zbar-0.10/zbar-gtk.pc
src/fastzbarlight/vendor/zbar-0.10/zbar-gtk.pc.in
src/fastzbarlight/vendor/zbar-0.10/zbar-qt.pc
src/fastzbarlight/vendor/zbar-0.10/zbar-qt.pc.in
src/fastzbarlight/vendor/zbar-0.10/zbar.ico
src/fastzbarlight/vendor/zbar-0.10/zbar.nsi
src/fastzbarlight/vendor/zbar-0.10/zbar.pc
src/fastzbarlight/vendor/zbar-0.10/zbar.pc.in
src/fastzbarlight/vendor/zbar-0.10/autom4te.cache/output.0
src/fastzbarlight/vendor/zbar-0.10/autom4te.cache/requests
src/fastzbarlight/vendor/zbar-0.10/autom4te.cache/traces.0
src/fastzbarlight/vendor/zbar-0.10/config/compile
src/fastzbarlight/vendor/zbar-0.10/config/config.guess
src/fastzbarlight/vendor/zbar-0.10/config/config.rpath
src/fastzbarlight/vendor/zbar-0.10/config/config.sub
src/fastzbarlight/vendor/zbar-0.10/config/depcomp
src/fastzbarlight/vendor/zbar-0.10/config/install-sh
