Metadata-Version: 1.1
Name: fastzbarlight
Version: 0.0.10
Summary: A fork of zbarlight, which includes a vendored copy of zbar compiled with optimization flags
Home-page: UNKNOWN
Author: UNKNOWN
Author-email: UNKNOWN
License: BSD
Keywords: zbar,QR code reader
Platform: UNKNOWN
Classifier: Development Status :: 5 - Production/Stable
Classifier: Intended Audience :: Developers
Classifier: License :: OSI Approved :: BSD License
Classifier: Natural Language :: English
Classifier: Operating System :: OS Independent
Classifier: Programming Language :: C
Classifier: Programming Language :: Python :: 2.6
Classifier: Programming Language :: Python :: 2.7
Classifier: Programming Language :: Python :: 3.3
Classifier: Programming Language :: Python :: 3.4
Classifier: Programming Language :: Python :: 3.5
Classifier: Topic :: Scientific/Engineering :: Image Recognition
